README.rst
setup.py
src/PysphereLibrary/__init__.py
src/PysphereLibrary/library.py
src/PysphereLibrary/version.py
src/robotframework_pyspherelibrary.egg-info/PKG-INFO
src/robotframework_pyspherelibrary.egg-info/SOURCES.txt
src/robotframework_pyspherelibrary.egg-info/dependency_links.txt
src/robotframework_pyspherelibrary.egg-info/requires.txt
src/robotframework_pyspherelibrary.egg-info/top_level.txt