Metadata-Version: 1.0
Name: robotframework-pyspherelibrary
Version: 1.0.0
Summary: Robot Framework test library for VMWare Services
Home-page: UNKNOWN
Author: UNKNOWN
Author-email: UNKNOWN
License: Apache License 2.0
Keywords: robotframework testing testautomation vmware pysphere
Platform: any
